zerohertzLib_test/__init__.py
zerohertzLib_test/algorithm/__init__.py
zerohertzLib_test/algorithm/bfs.py
zerohertzLib_test/algorithm/dfs.py
zerohertzLib_test-0.1.3.dist-info/LICENSE
zerohertzLib_test-0.1.3.dist-info/METADATA
zerohertzLib_test-0.1.3.dist-info/WHEEL
zerohertzLib_test-0.1.3.dist-info/top_level.txt
zerohertzLib_test-0.1.3.dist-info/RECORD
