Metadata-Version: 2.1
Name: zerohertzLib-test
Version: 0.1.3
Summary: Zerohertz's Library
Home-page: UNKNOWN
Author: Zerohertz
License: UNKNOWN
Platform: UNKNOWN
Requires-Python: >=3.7.0
